{"type":"object","properties":{"/api/prisma/:id":{"type":"object","properties":{"parameters":{"type":"object","properties":{"body":{"$ref":"#/definitions/Prisma.UserUpdateWithoutPostsInput"},"path":{"type":"object","properties":{"id":{"type":"string"}}},"query":{"type":"object","properties":{"query":{"type":"string"},"number":{"type":"number"}}}}},"responses":{"type":"object","properties":{"200":{}}},"errors":{"type":"object","properties":{"400":{"anyOf":[{"type":"object","properties":{"message":{"type":"string","const":"Bad Request"}}},{"const":"Not OK","type":"string"}]},"500":{"type":"object","properties":{"message":{"type":"string","const":"Internal Server Error"}}}}}}}},"definitions":{"__type":{"type":"object","properties":{"id":{"anyOf":[{"$ref":"#/definitions/Prisma.StringFieldUpdateOperationsInput"},{"type":"string"}]},"email":{"anyOf":[{"$ref":"#/definitions/Prisma.StringFieldUpdateOperationsInput"},{"type":"string"}]},"name":{"anyOf":[{"$ref":"#/definitions/Prisma.NullableStringFieldUpdateOperationsInput"},{"type":"string"}]},"password":{"anyOf":[{"$ref":"#/definitions/Prisma.StringFieldUpdateOperationsInput"},{"type":"string"}]},"createdAt":{"anyOf":[{"type":"string","format":"date-time"},{"$ref":"#/definitions/Prisma.DateTimeFieldUpdateOperationsInput"},{"type":"string"}]},"updatedAt":{"anyOf":[{"type":"string","format":"date-time"},{"$ref":"#/definitions/Prisma.DateTimeFieldUpdateOperationsInput"},{"type":"string"}]}}},"__type_1":{"type":"object","properties":{"set":{"type":"string"}}},"Prisma.StringFieldUpdateOperationsInput":{"$ref":"#/definitions/__type_1"},"__type_2":{"type":"object","properties":{"set":{"type":"string"}}},"Prisma.NullableStringFieldUpdateOperationsInput":{"$ref":"#/definitions/__type_2"},"__type_3":{"type":"object","properties":{"set":{"anyOf":[{"type":"string","format":"date-time"},{"type":"string"}]}}},"Prisma.DateTimeFieldUpdateOperationsInput":{"$ref":"#/definitions/__type_3"},"Prisma.UserUpdateWithoutPostsInput":{"$ref":"#/definitions/__type"}},"$schema":"http://json-schema.org/draft-07/schema#"}